LICENSE.txt
MANIFEST.in
README.rst
setup.py
annotation_refinery/__init__.py
annotation_refinery/download_files.py
annotation_refinery/go.py
annotation_refinery/idmap.py
annotation_refinery/loader.py
annotation_refinery/process_do.py
annotation_refinery/process_go.py
annotation_refinery/process_kegg.py
annotation_refinery/run_refinery.py
annotation_refinery/slugify.py
annotation_refinery/tests.py
annotation_refinery/utils.py
annotation_refinery.egg-info/PKG-INFO
annotation_refinery.egg-info/SOURCES.txt
annotation_refinery.egg-info/dependency_links.txt
annotation_refinery.egg-info/requires.txt
annotation_refinery.egg-info/top_level.txt