Metadata-Version: 1.1
Name: annotation-refinery
Version: 1.0.2
Summary: Portable Python package to process publicly available annotated sets of genes, such as Gene Ontology and Disease Ontologyterms.
Home-page: https://bitbucket.org/greenelab/annotation-refinery
Author: Greene Lab
Author-email: team@greenelab.com
License: LICENSE.txt
Platform: UNKNOWN
Classifier: Environment :: Web Environment
Classifier: Intended Audience :: Developers
Classifier: Intended Audience :: Science/Research
Classifier: License :: OSI Approved :: BSD License
Classifier: Operating System :: OS Independent
Classifier: Programming Language :: Python
Classifier: Programming Language :: Python :: 2.7
Classifier: Topic :: Scientific/Engineering :: Bio-Informatics
